nonebot_plugin_anime_downloader-0.2.2.dist-info/METADATA
nonebot_plugin_anime_downloader-0.2.2.dist-info/WHEEL
nonebot_plugin_anime_downloader-0.2.2.dist-info/licenses/LICENSE
nonebot_plugin_anime_downloader/__init__.py
nonebot_plugin_anime_downloader/acgrip/__init__.py
nonebot_plugin_anime_downloader/config.py
nonebot_plugin_anime_downloader/data_source.py
nonebot_plugin_anime_downloader/downloader/__init__.py
nonebot_plugin_anime_downloader/downloader/exceptions.py
nonebot_plugin_anime_downloader/downloader/models.py
nonebot_plugin_anime_downloader/models.py
nonebot_plugin_anime_downloader/routes.py
nonebot_plugin_anime_downloader/tasks.py
nonebot_plugin_anime_downloader/templates/index.html
nonebot_plugin_anime_downloader/utils.py
nonebot_plugin_anime_downloader-0.2.2.dist-info/RECORD
