Metadata-Version: 2.1
Name: nonebot-plugin-anime-downloader
Version: 0.2.2
Summary: ✨ 基于 qBittorrent Web UI 的番剧下载 NoneBot 插件 ✨
Author-Email: zhaomaoniu <2667292003@qq.com>
License: MIT
Requires-Python: >=3.8
Requires-Dist: nonebot2>=2.2.1
Requires-Dist: aiohttp>=3.9.5
Requires-Dist: qbittorrent-api>=2024.3.60
Requires-Dist: torrent-parser>=0.4.1
Requires-Dist: nonebot-plugin-apscheduler>=0.4.0
Requires-Dist: sqlalchemy>=2.0.29
Requires-Dist: nonebot-plugin-localstore>=0.6.0
Requires-Dist: opencc>=1.1.7
Requires-Dist: nonebot-plugin-alconna>=0.42.4
Requires-Dist: FastAPI>=0.111.0
Requires-Dist: uvicorn>=0.30.6
